django_hpo_terms-0.8.0.dist-info/DESCRIPTION.rst
django_hpo_terms-0.8.0.dist-info/METADATA
django_hpo_terms-0.8.0.dist-info/RECORD
django_hpo_terms-0.8.0.dist-info/WHEEL
django_hpo_terms-0.8.0.dist-info/metadata.json
django_hpo_terms-0.8.0.dist-info/top_level.txt
hpo_terms/__init__.py
hpo_terms/admin.py
hpo_terms/app_settings.py
hpo_terms/apps.py
hpo_terms/choices.py
hpo_terms/filters.py
hpo_terms/managers.py
hpo_terms/models.py
hpo_terms/schema.py
hpo_terms/serializers.py
hpo_terms/urls.py
hpo_terms/utils.py
hpo_terms/views.py
hpo_terms/viewsets.py
hpo_terms/management/__init__.py
hpo_terms/management/commands/__init__.py
hpo_terms/management/commands/hpo_sync.py
hpo_terms/management/commands/sync_hpo.py
hpo_terms/migrations/0001_initial.py
hpo_terms/migrations/__init__.py
