Metadata-Version: 2.0
Name: django-hpo-terms
Version: 0.8.0
Summary: Django app to parse, store, and update HPO terms
Home-page: https://github.com/genomics-geek/django-hpo-terms
Author: Michael A. Gonzalez
Author-email: genomics.geek.04.22@gmail.com
License: MIT
Keywords: django-hpo-terms
Platform: UNKNOWN
Classifier: Development Status :: 4 - Beta
Classifier: Framework :: Django
Classifier: Framework :: Django :: 1.11
Classifier: Framework :: Django :: 2.0
Classifier: Intended Audience :: Developers
Classifier: License :: OSI Approved :: BSD License
Classifier: Natural Language :: English
Classifier: Programming Language :: Python :: 3
Classifier: Programming Language :: Python :: 3.5
Classifier: Programming Language :: Python :: 3.6
Requires-Dist: djangorestframework (==3.7.7)
Requires-Dist: django-filter (==1.1.0)
Requires-Dist: django-genome (==0.6.0)
Requires-Dist: django-genomix (==0.6.0)
Requires-Dist: django-model-utils (==3.1.1)
Requires-Dist: django-user-activities (==0.5.0)
Requires-Dist: pronto (==0.10.2)
Requires-Dist: graphene-django (==2.0.0)
